architect_ai/__init__.py
architect_ai/architect.py
architect_ai/blueprint.py
architect_ai/blueprint_rack.py
architect_ai/build.py
architect_ai/client.py
architect_ai/concurrent_executable.py
architect_ai/decision_blueprint.py
architect_ai/execution_mode.py
architect_ai/logging_utils.py
architect_ai/py.typed
architect_ai/tool.py
architect_ai/toolbox.py
architect_ai/exceptions/__init__.py
architect_ai/exceptions/architect_exceptions.py
architect_ai/exceptions/tool_exceptions.py
architect_ai/exceptions/toolbox_exceptions.py
architect_ai-0.2.0.dist-info/licenses/LICENSE
architect_ai-0.2.0.dist-info/METADATA
architect_ai-0.2.0.dist-info/WHEEL
architect_ai-0.2.0.dist-info/top_level.txt
architect_ai-0.2.0.dist-info/RECORD
