Metadata-Version: 2.4
Name: architect-ai
Version: 0.2.0
Summary: AI-powered workflow orchestration system with custom tools and blueprints
Author-email: Architect AI Team <team@architect-ai.com>
License: MIT
Project-URL: Homepage, https://github.com/architect-ai/architect-ai
Project-URL: Repository, https://github.com/architect-ai/architect-ai.git
Project-URL: Documentation, https://architect-ai.readthedocs.io/
Project-URL: Issues, https://github.com/architect-ai/architect-ai/issues
Keywords: ai,llm,workflow,orchestration,openai,automation,tools,blueprints
Classifier: Development Status :: 3 - Alpha
Classifier: Intended Audience :: Developers
Classifier: License :: OSI Approved :: MIT License
Classifier: Programming Language :: Python :: 3
Classifier: Programming Language :: Python :: 3.9
Classifier: Programming Language :: Python :: 3.10
Classifier: Programming Language :: Python :: 3.11
Classifier: Programming Language :: Python :: 3.12
Classifier: Topic :: Software Development :: Libraries :: Python Modules
Classifier: Topic :: Scientific/Engineering :: Artificial Intelligence
Requires-Python: >=3.9
License-File: LICENSE
Requires-Dist: openai>=1.0.0
Requires-Dist: psutil>=5.9.0
Requires-Dist: ujson>=5.8.0
Provides-Extra: dev
Requires-Dist: pytest>=7.0.0; extra == "dev"
Requires-Dist: pytest-cov>=4.0.0; extra == "dev"
Requires-Dist: pytest-asyncio>=0.21.0; extra == "dev"
Requires-Dist: black>=23.0.0; extra == "dev"
Requires-Dist: flake8>=6.0.0; extra == "dev"
Requires-Dist: mypy>=1.0.0; extra == "dev"
Dynamic: license-file
